ansys/tools/example_coverage/__init__.py
ansys/tools/example_coverage/__main__.py
ansys/tools/example_coverage/_version.py
ansys/tools/example_coverage/example_coverage.py
ansys_tools_example_coverage-0.1.dev0.dist-info/LICENSE
ansys_tools_example_coverage-0.1.dev0.dist-info/METADATA
ansys_tools_example_coverage-0.1.dev0.dist-info/WHEEL
ansys_tools_example_coverage-0.1.dev0.dist-info/top_level.txt
ansys_tools_example_coverage-0.1.dev0.dist-info/RECORD
