Metadata-Version: 2.1
Name: ansys-tools-example-coverage
Version: 0.1.dev0
Summary: Tools to assess the docstring examples coverage.
Home-page: https://github.com/pyansys/example-coverage
Author: ANSYS, Inc.
Maintainer-email: maxime.rey@ansys.com
License: UNKNOWN
Project-URL: Bug Tracker, https://github.com/pyansys/example-coverage/issues
Platform: UNKNOWN
Classifier: Programming Language :: Python :: 3
Classifier: License :: OSI Approved :: MIT License
Classifier: Operating System :: OS Independent
Requires-Python: >=3.6
License-File: LICENSE
